README.md
setup.py
flake8_typehinting/__init__.py
flake8_typehinting/flake8_typehinting.py
flake8_typehinting.egg-info/PKG-INFO
flake8_typehinting.egg-info/SOURCES.txt
flake8_typehinting.egg-info/dependency_links.txt
flake8_typehinting.egg-info/entry_points.txt
flake8_typehinting.egg-info/requires.txt
flake8_typehinting.egg-info/top_level.txt